codebreak/__init__.py
codebreak/eye_exercises.py
codebreak/mental_exercises.py
codebreak/physical_exercise.py
codebreak/stretches.py
codebreak-0.1.dist-info/LICENSE
codebreak-0.1.dist-info/METADATA
codebreak-0.1.dist-info/WHEEL
codebreak-0.1.dist-info/top_level.txt
codebreak-0.1.dist-info/RECORD
